precise/__init__.py
precise/annoyance_estimator.py
precise/functions.py
precise/model.py
precise/network_runner.py
precise/params.py
precise/stats.py
precise/threshold_decoder.py
precise/train_data.py
precise/util.py
precise/vectorization.py
precise/data/activate.wav
precise/pocketsphinx/__init__.py
precise/pocketsphinx/listener.py
precise/pocketsphinx/scripts/__init__.py
precise/pocketsphinx/scripts/listen.py
precise/pocketsphinx/scripts/test.py
precise/scripts/add_noise.py
precise/scripts/base_script.py
precise/scripts/calc_threshold.py
precise/scripts/collect.py
precise/scripts/convert.py
precise/scripts/engine.py
precise/scripts/eval.py
precise/scripts/graph.py
precise/scripts/listen.py
precise/scripts/simulate.py
precise/scripts/test.py
precise/scripts/train.py
precise/scripts/train_generated.py
precise/scripts/train_incremental.py
precise/scripts/train_optimize.py
precise/scripts/train_sampled.py
liant_precise-1.0.0.dev4.dist-info/LICENSE
liant_precise-1.0.0.dev4.dist-info/METADATA
liant_precise-1.0.0.dev4.dist-info/WHEEL
liant_precise-1.0.0.dev4.dist-info/entry_points.txt
liant_precise-1.0.0.dev4.dist-info/top_level.txt
liant_precise-1.0.0.dev4.dist-info/RECORD
